rotsim2d/__init__.py
rotsim2d/couple.py
rotsim2d/dressedleaf.py
rotsim2d/pathways.py
rotsim2d/propagate.py
rotsim2d/py.typed
rotsim2d/rcpeaks.py
rotsim2d/rcs.py
rotsim2d/utils.py
rotsim2d/symbolic/__init__.py
rotsim2d/symbolic/common.py
rotsim2d/symbolic/functions.py
rotsim2d/symbolic/results.py
rotsim2d/visual/__init__.py
rotsim2d/visual/functions.py
rotsim2d/visual/latexprinter.py
rotsim2d-0.9.2.dist-info/LICENSE
rotsim2d-0.9.2.dist-info/METADATA
rotsim2d-0.9.2.dist-info/WHEEL
rotsim2d-0.9.2.dist-info/top_level.txt
rotsim2d-0.9.2.dist-info/RECORD
