Metadata-Version: 2.1
Name: rotsim2d
Version: 0.9.2
Summary: Simulate 2D rovibrational spectra of gas-phase molecular samples
Home-page: https://github.com/gkowzan/rotsim2d
Author: Grzegorz Kowzan
Author-email: gkowzan@umk.pl
License: MIT License
Classifier: Development Status :: 4 - Beta
Classifier: Environment :: Console
Classifier: Intended Audience :: Science/Research
Classifier: Programming Language :: Python :: 3
Classifier: Programming Language :: Python :: 3.6
Classifier: Programming Language :: Python :: 3.7
Classifier: Programming Language :: Python :: 3.8
Classifier: Programming Language :: Python :: 3.9
Classifier: Programming Language :: Python :: 3.10
Classifier: Topic :: Scientific/Engineering :: Physics
Classifier: Topic :: Scientific/Engineering :: Chemistry
Classifier: Typing :: Typed
Classifier: License :: OSI Approved :: MIT License
Requires-Python: >=3.7
License-File: LICENSE
Requires-Dist: attrs (>=21.4.0)
Requires-Dist: asteval (>=0.9.25)
Requires-Dist: h5py (>=3.1)
Requires-Dist: numpy (>=1.16.5)
Requires-Dist: scipy (>=1.3)
Requires-Dist: anytree (>=2.8.0)
Requires-Dist: sympy (<=1.9,>=1.8)
Requires-Dist: matplotlib (>=2.2.3)
Requires-Dist: molspecutils (>=0.3.0)
Requires-Dist: importlib-metadata (>=1.0) ; python_version < "3.8"
Provides-Extra: doc
Requires-Dist: Sphinx ; extra == 'doc'
Requires-Dist: sphinx-book-theme ; extra == 'doc'
Requires-Dist: ipython ; extra == 'doc'
Requires-Dist: ipykernel ; extra == 'doc'
Requires-Dist: jupyter-client ; extra == 'doc'
Requires-Dist: sphinx-copybutton ; extra == 'doc'
Provides-Extra: pyfftw
Requires-Dist: pyfftw ; extra == 'pyfftw'
Provides-Extra: test
Requires-Dist: pytest ; extra == 'test'
Requires-Dist: gkpywigxjpf ; (platform_system == "Linux") and extra == 'test'
